asarPy/__init__.py
asarPy/asar.py
asarPy-1.0.dist-info/LICENSE
asarPy-1.0.dist-info/METADATA
asarPy-1.0.dist-info/WHEEL
asarPy-1.0.dist-info/top_level.txt
asarPy-1.0.dist-info/RECORD
